topsis/__init__.py
topsis/__main__.py
Topsis_Rishabh_102003393-1.0.dist-info/LICENSE
Topsis_Rishabh_102003393-1.0.dist-info/METADATA
Topsis_Rishabh_102003393-1.0.dist-info/WHEEL
Topsis_Rishabh_102003393-1.0.dist-info/entry_points.txt
Topsis_Rishabh_102003393-1.0.dist-info/top_level.txt
Topsis_Rishabh_102003393-1.0.dist-info/RECORD
