Metadata-Version: 2.1
Name: Topsis-Rishabh-102003393
Version: 1.0
Summary: This a Topsis package,TOPSIS (technique for order performance by similarity to ideal solution) is a useful technique in dealing with multi-attribute or multi-criteria decision making (MADM/MCDM) problems in the real world 
Author: Rishabh Handoo
Author-email: rhandoo_be20@thapar.edu
License-File: LICENSE
Requires-Dist: pandas
